tests/__init__.py
tests/helper.py
tests/test_env.py
tests/localtests/__init__.py
tests/localtests/test_validate.py
tests/localtests/test_wrap.py
tests/unittests/__init__.py
tests/unittests/test_annot_record.py
tests/unittests/test_fasta.py
tests/unittests/test_fasta_dna.py
tests/unittests/test_fastq.py
tests/unittests/test_gbk.py
tests/unittests/test_gff.py
tests/unittests/test_gtf.py
tests/unittests/test_pubmed_xml.py
biofile-0.0.10.dist-info/METADATA
biofile-0.0.10.dist-info/WHEEL
biofile-0.0.10.dist-info/top_level.txt
biofile-0.0.10.dist-info/RECORD
