Metadata-Version: 2.1
Name: biofile
Version: 0.0.10
Summary: Process various file format for RNA-Seq data analysis
Home-page: https://github.com/Tiezhengyuan/bio_file
Author: Tiezheng Yuan
Author-email: tiezhengyuan@hotmail.com
Keywords: pypi,cicd,python
Classifier: Development Status :: 1 - Planning
Classifier: Intended Audience :: Developers
Classifier: Programming Language :: Python :: 3
Classifier: Operating System :: Unix
Classifier: Operating System :: MacOS :: MacOS X
Classifier: Operating System :: Microsoft :: Windows
Requires-Dist: Bio
Requires-Dist: biosequtils
Requires-Dist: numpy
Requires-Dist: pandas
